st_cli/__init__.py
st_cli/base.py
st_cli/client.py
st_cli/const.py
st_cli/gpu_machines.py
st_cli/job.py
st_cli/launch.py
st_cli/list.py
st_cli/login.py
st_cli/main.py
st_cli/sg_inference.py
st_cli/stop.py
st_cli/utils.py
st_cli/view.py
st_cli/visualisation.py
st_cli/workstation.py
st_cli/datamodels/.git
st_cli/datamodels/.gitignore
st_cli/datamodels/README.md
st_cli/datamodels/requirements.txt
st_cli/datamodels/datamodels/__init__.py
st_cli/datamodels/datamodels/api/__init__.py
st_cli/datamodels/datamodels/cli/__init__.py
st_cli/datamodels/datamodels/common/__init__.py
st_cli/datamodels/datamodels/jc/__init__.py
st_cli/datamodels/datamodels/sg_finetune/__init__.py
st_cli/sg_finetune/__init__.py
st_cli/sg_finetune/clm.py
st_cli/sg_finetune/sent_transformers.py
st_cli/sg_finetune/seq2seq.py
st_cli/sg_finetune/text_classification.py
st_cli/sg_finetune/token_classification.py
scalegen_cli-0.0.46.dist-info/METADATA
scalegen_cli-0.0.46.dist-info/WHEEL
scalegen_cli-0.0.46.dist-info/entry_points.txt
scalegen_cli-0.0.46.dist-info/top_level.txt
scalegen_cli-0.0.46.dist-info/RECORD
