Metadata-Version: 2.1
Name: scalegen-cli
Version: 0.0.46
Summary: ScaleGenAI CLI
Requires-Python: >=3.8
Requires-Dist: certifi==2021.10.8
Requires-Dist: charset-normalizer==2.0.11
Requires-Dist: checksumdir==1.2.0
Requires-Dist: click==8.0.3
Requires-Dist: colorama==0.4.4
Requires-Dist: commonmark==0.9.1
Requires-Dist: idna==3.3
Requires-Dist: jmespath==0.10.0
Requires-Dist: ordered-set==4.1.0
Requires-Dist: progress==1.6
Requires-Dist: pycryptodomex==3.12.0
Requires-Dist: pydantic==2.4.2
Requires-Dist: Pygments==2.11.2
Requires-Dist: python-dateutil==2.8.2
Requires-Dist: pytz==2021.3
Requires-Dist: PyYAML==5.3.1
Requires-Dist: requests==2.27.1
Requires-Dist: rich==11.0.0
Requires-Dist: six==1.16.0
Requires-Dist: termcolor==1.1.0
Requires-Dist: urllib3==1.26.8
Requires-Dist: zstandard==0.20.0
Requires-Dist: black==24.2.0
Requires-Dist: requests==2.27.1
Requires-Dist: cython<3.0.0
Requires-Dist: setuptools==72.1.0
